Workbook

Sheet Dashboard & Resumo
A1: SISTEMA INTEGRADO DE DECLAÇÃO DE IMPOSTO DE RENDA
A2: Consolidação anual automatizada de rendimentos, despesas, bens e proventos.
A4: TOTAL RENDIMENTOS TRIBUTÁVEIS | C4: TOTAL DESPESAS DEDUTÍVEIS | E4: PATRIMÔNIO LÍQUIDO (31/12) | G4: PROVENTOS INVESTIMENTOS
A5: =SUM('Rendimentos'!E8:E100) | C5: =SUM('Despesas Dedutíveis'!F8:F100) | E5: =SUM('Bens e Direitos'!E8:E100) | G5: =SUM('Investimentos'!G8:G100)
A7: CONSOLIDAÇÃO DE DADOS PARA PREENCHIMENTO DO PGFN / RECEITA
A8: Métrica / Grupo Fiscal | B8: Aba de Origem | C8: Fórmula de Apuração | D8: Valor Consolidado (R$)
A9: Total de Rendimentos Tributáveis | B9: Rendimentos | C9: =SUM('Rendimentos'!E8:E100) | D9: =SUM('Rendimentos'!E8:E100)
A10: Total de Imposto Retido na Fonte (IRRF) | B10: Rendimentos | C10: =SUM('Rendimentos'!F8:F100) | D10: =SUM('Rendimentos'!F8:F100)
A11: Total de Contribuição Previdenciária (INSS) | B11: Rendimentos | C11: =SUM('Rendimentos'!G8:G100) | D11: =SUM('Rendimentos'!G8:G100)
A12: Rendimentos Isentos e Não Tributáveis | B12: Rendimentos | C12: =SUMIFS('Rendimentos'!E8:E100, 'Rendimentos'!D8:D100, "Rendimento Isento") | D12: =SUMIFS('Rendimentos'!E8:E100, 'Rendimentos'!D8:D100, "Rendimento Isento")
A13: Total de Despesas Dedutíveis - Saúde | B13: Despesas Dedutíveis | C13: =SUMIFS('Despesas Dedutíveis'!F8:F100, 'Despesas Dedutíveis'!D8:D100, "Saúde") | D13: =SUMIFS('Despesas Dedutíveis'!F8:F100, 'Despesas Dedutíveis'!D8:D100, "Saúde")
A14: Total de Despesas Dedutíveis - Educação | B14: Despesas Dedutíveis | C14: =SUMIFS('Despesas Dedutíveis'!F8:F100, 'Despesas Dedutíveis'!D8:D100, "Educação") | D14: =SUMIFS('Despesas Dedutíveis'!F8:F100, 'Despesas Dedutíveis'!D8:D100, "Educação")
A15: Total Geral de Despesas Dedutíveis | B15: Despesas Dedutíveis | C15: =SUM('Despesas Dedutíveis'!F8:F100) | D15: =SUM('Despesas Dedutíveis'!F8:F100)
A16: Evolução Patrimonial Total (Bens e Direitos em 31/12) | B16: Bens e Direitos | C16: =SUM('Bens e Direitos'!E8:E100) | D16: =SUM('Bens e Direitos'!E8:E100)
A17: Variação Patrimonial Anual (Aportes e Reformas) | B17: Bens e Direitos | C17: =SUM('Bens e Direitos'!D8:D100) | D17: =SUM('Bens e Direitos'!D8:D100)
A18: Total Investido em Renda Fixa / Variável | B18: Investimentos | C18: =SUM('Investimentos'!F8:F100) | D18: =SUM('Investimentos'!F8:F100)
A19: Total de Proventos/Rendimentos Recebidos | B19: Investimentos | C19: =SUM('Investimentos'!G8:G100) | D19: =SUM('Investimentos'!G8:G100)
A20: Total de Lucro/Prejuízo em Criptoativos | B20: Criptoativos | C20: =SUM('Criptoativos'!G8:G100) | D20: =SUM('Criptoativos'!G8:G100)
A21: Total de Dívidas e Ônus Reais em 31/12 | B21: Dívidas e Ônus | C21: =SUM('Dívidas e Ônus'!E8:E100) | D21: =SUM('Dívidas e Ônus'!E8:E100)

Sheet Rendimentos
A1: REGISTRO DETALHADO DE RENDIMENTOS TRIBUTÁVEIS E ISENTOS
A2: Mapeie salários, pró-labore, serviços prestados e lucros distribuídos.
A7: Data / Mês | B7: Fonte Pagadora | C7: CPF / CNPJ | D7: Categoria | E7: Rendimento Bruto (R$) | F7: IRRF Retido (R$) | G7: INSS (R$) | H7: Observações / Recibo
A8: Jan/2025 | B8: Empresa Exemplo S.A. | C8: 00.000.000/0001-00 | D8: Trabalho Assalariado | E8: 5000 | F8: 350 | G8: 550 | H8: Informe de Rendimentos Anual
A9: Fev/2025 | B9: Empresa Exemplo S.A. | C9: 00.000.000/0001-00 | D9: Trabalho Assalariado | E9: 5000 | F9: 350 | G9: 550 | H9: Informe de Rendimentos Anual
A10: Mar/2025 | B10: Cliente Pessoa Física | C10: 111.222.333-44 | D10: Prestação de Serviço | E10: 1200 | F10: 0 | G10: 0 | H10: Recibo Emitido - Carnê-Leão
A11: Dez/2025 | B11: Banco Exemplo S.A. | C11: 99.888.777/0001-11 | D11: Rendimento Isento | E11: 450 | F11: 0 | G11: 0 | H11: Rendimento LCI/LCA
A100: TOTAL CONSOLIDADO | E100: =SUM(E8:E99) | F100: =SUM(F8:F99) | G100: =SUM(G8:G99)

Sheet Despesas Dedutíveis
A1: REGISTRO DE DESPESAS DEDUTÍVEIS (SAÚDE, EDUCAÇÃO, PGBL)
A2: Gasto que abate a base de cálculo do IRPF no modelo completo.
A7: Data | B7: Beneficiário / Prestador | C7: CPF / CNPJ | D7: Categoria | E7: Descrição do Serviço | F7: Valor Pago (R$) | G7: Comprovante Salvo? | H7: Titular / Dependente
A8: 15/03/2025 | B8: Dr. Carlos Eduardo (Dentista) | C8: 222.333.444-55 | D8: Saúde | E8: Tratamento Odontológico | F8: 850 | G8: Sim | H8: Titular
A9: 05/05/2025 | B9: Instituto de Ensino Alfa | C9: 12.345.678/0001-90 | D9: Educação | E9: Mensalidade Graduação/Técnico | F9: 650 | G9: Sim | H9: Titular
A10: 10/08/2025 | B10: Clínica Médica Vida | C10: 98.765.432/0001-10 | D10: Saúde | E10: Consulta Especializada | F10: 300 | G10: Sim | H10: Dependente
A100: TOTAL CONSOLIDADO | F100: =SUM(F8:F99)

Sheet Bens e Direitos
A1: DECLARAÇÃO DE BENS E DIREITOS (PATRIMÔNIO)
A2: Mantenha o histórico pelo custo de aquisição. Nunca atualize pelo valor de mercado.
A7: Código IRPF | B7: Discriminação / Descrição Detalhada do Bem | C7: Situação em 31/12/2024 (R$) | D7: Aportes / Melhorias no Ano (R$) | E7: Situação em 31/12/2025 (R$)
A8: 01 - Imóveis | B8: Apartamento residencial na Rua X, Nº 100, Bairro Y. Adquirido via financiamento. | C8: 180000 | D8: 12000 | E8: =C8+D8
A9: 02 - Veículos | B9: Veículo automotor Marca Model, Placa ABC-1234. Quitado. | C9: 45000 | D9: 0 | E9: =C9+D9
A10: 06 - Depósitos | B10: Conta Corrente Banco Z, Agência 0001, Conta 12345-6. | C10: 3200.5 | D10: 1499.5 | E10: =C10+D10
A100: TOTAL CONSOLIDADO | C100: =SUM(C8:C99) | D100: =SUM(D8:D99) | E100: =SUM(E8:E99)

Sheet Investimentos
A1: CARTEIRA DE INVESTIMENTOS (RENDA FIXA, AÇÕES, FIIs)
A2: Apuração de posição patrimonial em ativos financeiros e proventos recebidos.
A7: Ativo / Ticker | B7: Instituição Custodiante | C7: Tipo de Ativo | D7: Quantidade | E7: Preço Médio (R$) | F7: Total Investido (R$) | G7: Proventos / Rendimentos no Ano (R$)
A8: CDB Banco X | B8: Corretora A | C8: Renda Fixa | D8: 1 | E8: 5000 | F8: =D8*E8 | G8: 525
A9: BBAS3 | B9: Corretora A | C9: Ações | D9: 100 | E9: 27.5 | F9: =D9*E9 | G9: 210
A10: KNCR11 | B10: Corretora B | C10: FIIs | D10: 50 | E10: 101.2 | F10: =D10*E10 | G10: 580
A100: TOTAL CONSOLIDADO | F100: =SUM(F8:F99) | G100: =SUM(G8:G99)

Sheet Criptoativos
A1: DECLARAÇÃO E OPERAÇÕES COM CRIPTOATIVOS
A2: Registro obrigatório para saldos acima de R$ 5.000 por classe de criptoativo.
A7: Criptomoeda / Token | B7: Exchange / Carteira Custodiante | C7: Quantidade Possuída | D7: Custo Médio de Aquisição (R$) | E7: Valor Total Investido (R$) | F7: Vendas no Ano (R$) | G7: Lucro / Prejuízo Isento (R$)
A8: Bitcoin (BTC) | B8: Exchange Nacional X | C8: 0.025 | D8: 320000 | E8: =C8*D8 | F8: 0 | G8: 0
A9: Ethereum (ETH) | B9: Carteira Metamask | C9: 0.5 | D9: 18000 | E9: =C9*D9 | F9: 5000 | G9: 800
A100: TOTAL CONSOLIDADO | E100: =SUM(E8:E99) | F100: =SUM(F8:F99) | G100: =SUM(G8:G99)

Sheet Dívidas e Ônus
A1: DÍVIDAS E ÔNUS REAIS
A2: Informe empréstimos e dívidas acima de R$ 5.000 existentes em 31/12.
A7: Código IRPF | B7: Credor / Instituição | C7: CPF / CNPJ Credor | D7: Discriminação da Dívida | E7: Situação em 31/12/2024 (R$) | F7: Situação em 31/12/2025 (R$)
A8: 11 - Empréstimos | B8: Banco Exemplo S.A. | C8: 00.000.000/0001-00 | D8: Empréstimo Pessoal Consignado | E8: 15000 | F8: 8500
A9: 12 - Outras Dívidas | B9: Pessoa Física Exemplo | C9: 111.222.333-44 | D9: Mútuo Financeiro Particular | E9: 5000 | F9: 2000
A100: TOTAL CONSOLIDADO | E100: =SUM(E8:E99) | F100: =SUM(F8:F99)
